kreeck/__init__.py
kreeck/analyser.py
kreeck/cli.py
kreeck/hooks.py
tests/__init__.py
tests/test_analyser.py
kreeck-0.1.2.dist-info/METADATA
kreeck-0.1.2.dist-info/WHEEL
kreeck-0.1.2.dist-info/entry_points.txt
kreeck-0.1.2.dist-info/top_level.txt
kreeck-0.1.2.dist-info/RECORD
