Metadata-Version: 2.1
Name: kreeck
Version: 0.1.2
Summary: A tool to track Git contributions, generate detailed reports, and motivate contributors.
Home-page: https://github.com/kreeckacademy/kreeeckAnalyser
Author: Kreeck
Author-email: dave@kreeck.com
Classifier: Programming Language :: Python :: 3
Classifier: License :: OSI Approved :: MIT License
Classifier: Operating System :: OS Independent
Requires-Python: >=3.6
Requires-Dist: GitPython
Requires-Dist: pandas
Requires-Dist: matplotlib
Requires-Dist: python-dotenv
Requires-Dist: tqdm
Requires-Dist: requests
